{"box_data": [{"position": {"minX": 17.5, "minY": 100.3125, "maxX": 649.0, "maxY": 287.5}, "class_id": 0, "box_caption": "plate_cold 0.820", "scores": {"class_score": 0.8203125}, "domain": "pixel"}, {"position": {"minX": 19.78125, "minY": 212.75, "maxX": 98.375, "maxY": 254.5}, "class_id": 0, "box_caption": "plate_cold 0.546", "scores": {"class_score": 0.5458984375}, "domain": "pixel"}, {"position": {"minX": 25.875, "minY": 200.625, "maxX": 93.375, "maxY": 243.875}, "class_id": 0, "box_caption": "plate_cold 0.119", "scores": {"class_score": 0.1187744140625}, "domain": "pixel"}, {"position": {"minX": 12.375, "minY": 206.5, "maxX": 79.875, "maxY": 252.5}, "class_id": 0, "box_caption": "plate_cold 0.052", "scores": {"class_score": 0.052215576171875}, "domain": "pixel"}, {"position": {"minX": 4.96875, "minY": 207.0, "maxX": 102.25, "maxY": 264.0}, "class_id": 0, "box_caption": "plate_cold 0.032", "scores": {"class_score": 0.032318115234375}, "domain": "pixel"}, {"position": {"minX": 15.125, "minY": 183.75, "maxX": 91.25, "maxY": 248.25}, "class_id": 0, "box_caption": "plate_cold 0.016", "scores": {"class_score": 0.016326904296875}, "domain": "pixel"}, {"position": {"minX": 14.21875, "minY": 214.5, "maxX": 89.625, "maxY": 280.75}, "class_id": 0, "box_caption": "plate_cold 0.014", "scores": {"class_score": 0.01393890380859375}, "domain": "pixel"}, {"position": {"minX": 530.5, "minY": 107.25, "maxX": 657.5, "maxY": 292.0}, "class_id": 0, "box_caption": "plate_cold 0.011", "scores": {"class_score": 0.01139068603515625}, "domain": "pixel"}, {"position": {"minX": 19.09375, "minY": 193.375, "maxX": 117.375, "maxY": 251.375}, "class_id": 0, "box_caption": "plate_cold 0.009", "scores": {"class_score": 0.00934600830078125}, "domain": "pixel"}, {"position": {"minX": 32.09375, "minY": 189.25, "maxX": 102.125, "maxY": 239.5}, "class_id": 0, "box_caption": "plate_cold 0.008", "scores": {"class_score": 0.00751495361328125}, "domain": "pixel"}, {"position": {"minX": 25.03125, "minY": 177.875, "maxX": 94.625, "maxY": 230.875}, "class_id": 0, "box_caption": "plate_cold 0.005", "scores": {"class_score": 0.00537109375}, "domain": "pixel"}, {"position": {"minX": 14.75, "minY": 152.625, "maxX": 660.0, "maxY": 235.125}, "class_id": 0, "box_caption": "plate_cold 0.005", "scores": {"class_score": 0.00522613525390625}, "domain": "pixel"}, {"position": {"minX": -61.3125, "minY": 195.75, "maxX": 199.75, "maxY": 266.0}, "class_id": 0, "box_caption": "plate_cold 0.005", "scores": {"class_score": 0.004878997802734375}, "domain": "pixel"}, {"position": {"minX": 21.75, "minY": 92.875, "maxX": 217.625, "maxY": 239.375}, "class_id": 0, "box_caption": "plate_cold 0.005", "scores": {"class_score": 0.0046844482421875}, "domain": "pixel"}, {"position": {"minX": 525.5, "minY": 319.5, "maxX": 747.5, "maxY": 392.0}, "class_id": 0, "box_caption": "plate_cold 0.004", "scores": {"class_score": 0.004352569580078125}, "domain": "pixel"}, {"position": {"minX": 24.90625, "minY": 170.25, "maxX": 110.875, "maxY": 214.5}, "class_id": 0, "box_caption": "plate_cold 0.004", "scores": {"class_score": 0.004070281982421875}, "domain": "pixel"}, {"position": {"minX": 14.59375, "minY": 94.0, "maxX": 59.34375, "maxY": 123.0}, "class_id": 0, "box_caption": "plate_cold 0.004", "scores": {"class_score": 0.003871917724609375}, "domain": "pixel"}, {"position": {"minX": 457.25, "minY": 98.0, "maxX": 657.0, "maxY": 280.25}, "class_id": 0, "box_caption": "plate_cold 0.004", "scores": {"class_score": 0.00384521484375}, "domain": "pixel"}, {"position": {"minX": 30.28125, "minY": 175.5, "maxX": 138.5, "maxY": 224.75}, "class_id": 0, "box_caption": "plate_cold 0.004", "scores": {"class_score": 0.003772735595703125}, "domain": "pixel"}, {"position": {"minX": 363.75, "minY": 236.25, "maxX": 895.0, "maxY": 456.75}, "class_id": 0, "box_caption": "plate_cold 0.004", "scores": {"class_score": 0.003566741943359375}, "domain": "pixel"}, {"position": {"minX": 33.0, "minY": -55.40625, "maxX": 653.0, "maxY": 157.625}, "class_id": 0, "box_caption": "plate_cold 0.003", "scores": {"class_score": 0.003429412841796875}, "domain": "pixel"}, {"position": {"minX": 17.5, "minY": 169.75, "maxX": 108.1875, "maxY": 240.75}, "class_id": 0, "box_caption": "plate_cold 0.003", "scores": {"class_score": 0.00325775146484375}, "domain": "pixel"}, {"position": {"minX": 451.75, "minY": 330.75, "maxX": 809.0, "maxY": 396.25}, "class_id": 0, "box_caption": "plate_cold 0.003", "scores": {"class_score": 0.0031719207763671875}, "domain": "pixel"}, {"position": {"minX": 5.34375, "minY": 207.0, "maxX": 129.75, "maxY": 284.0}, "class_id": 0, "box_caption": "plate_cold 0.003", "scores": {"class_score": 0.0028896331787109375}, "domain": "pixel"}, {"position": {"minX": 15.0, "minY": 171.375, "maxX": 89.625, "maxY": 220.375}, "class_id": 0, "box_caption": "plate_cold 0.003", "scores": {"class_score": 0.00258636474609375}, "domain": "pixel"}, {"position": {"minX": 4.5625, "minY": 219.25, "maxX": 71.125, "maxY": 261.0}, "class_id": 0, "box_caption": "plate_cold 0.002", "scores": {"class_score": 0.00249481201171875}, "domain": "pixel"}, {"position": {"minX": -16.046875, "minY": 158.875, "maxX": 34.1875, "maxY": 262.25}, "class_id": 0, "box_caption": "plate_cold 0.002", "scores": {"class_score": 0.0024585723876953125}, "domain": "pixel"}, {"position": {"minX": 9.15625, "minY": 213.0, "maxX": 48.9375, "maxY": 258.5}, "class_id": 0, "box_caption": "plate_cold 0.002", "scores": {"class_score": 0.002208709716796875}, "domain": "pixel"}, {"position": {"minX": 26.4375, "minY": 149.625, "maxX": 144.25, "maxY": 223.625}, "class_id": 0, "box_caption": "plate_cold 0.002", "scores": {"class_score": 0.0021533966064453125}, "domain": "pixel"}, {"position": {"minX": 326.75, "minY": 104.25, "maxX": 650.0, "maxY": 275.25}, "class_id": 0, "box_caption": "plate_cold 0.002", "scores": {"class_score": 0.0021381378173828125}, "domain": "pixel"}, {"position": {"minX": 624.0, "minY": 302.75, "maxX": 646.0, "maxY": 385.25}, "class_id": 0, "box_caption": "plate_cold 0.002", "scores": {"class_score": 0.0020847320556640625}, "domain": "pixel"}, {"position": {"minX": -12.84375, "minY": 209.5, "maxX": 31.8125, "maxY": 292.0}, "class_id": 0, "box_caption": "plate_cold 0.002", "scores": {"class_score": 0.0020465850830078125}, "domain": "pixel"}, {"position": {"minX": 28.0625, "minY": 101.5625, "maxX": 277.25, "maxY": 290.25}, "class_id": 0, "box_caption": "plate_cold 0.002", "scores": {"class_score": 0.0020389556884765625}, "domain": "pixel"}, {"position": {"minX": -16.40625, "minY": 195.375, "maxX": 33.84375, "maxY": 273.25}, "class_id": 0, "box_caption": "plate_cold 0.002", "scores": {"class_score": 0.0019006729125976562}, "domain": "pixel"}, {"position": {"minX": -8.984375, "minY": 89.25, "maxX": 29.265625, "maxY": 141.0}, "class_id": 0, "box_caption": "plate_cold 0.002", "scores": {"class_score": 0.0016965866088867188}, "domain": "pixel"}, {"position": {"minX": 16.15625, "minY": 173.0, "maxX": 74.625, "maxY": 237.0}, "class_id": 0, "box_caption": "plate_cold 0.002", "scores": {"class_score": 0.0016279220581054688}, "domain": "pixel"}, {"position": {"minX": 554.0, "minY": -13.59375, "maxX": 717.0, "maxY": 104.625}, "class_id": 0, "box_caption": "plate_cold 0.001", "scores": {"class_score": 0.0014295578002929688}, "domain": "pixel"}, {"position": {"minX": 8.390625, "minY": 195.125, "maxX": 68.1875, "maxY": 248.625}, "class_id": 0, "box_caption": "plate_cold 0.001", "scores": {"class_score": 0.0014286041259765625}, "domain": "pixel"}, {"position": {"minX": 11.984375, "minY": 100.6875, "maxX": 47.0, "maxY": 147.25}, "class_id": 0, "box_caption": "plate_cold 0.001", "scores": {"class_score": 0.0014057159423828125}, "domain": "pixel"}, {"position": {"minX": 15.5703125, "minY": 96.875, "maxX": 42.125, "maxY": 130.5}, "class_id": 0, "box_caption": "plate_cold 0.001", "scores": {"class_score": 0.0014009475708007812}, "domain": "pixel"}, {"position": {"minX": -34.4375, "minY": 207.875, "maxX": 169.75, "maxY": 273.75}, "class_id": 0, "box_caption": "plate_cold 0.001", "scores": {"class_score": 0.0013942718505859375}, "domain": "pixel"}, {"position": {"minX": -4.4765625, "minY": 74.375, "maxX": 28.0, "maxY": 132.375}, "class_id": 0, "box_caption": "plate_cold 0.001", "scores": {"class_score": 0.0013055801391601562}, "domain": "pixel"}, {"position": {"minX": 17.03125, "minY": 227.625, "maxX": 71.125, "maxY": 290.25}, "class_id": 0, "box_caption": "plate_cold 0.001", "scores": {"class_score": 0.0012845993041992188}, "domain": "pixel"}, {"position": {"minX": -6.625, "minY": 146.0, "maxX": 169.25, "maxY": 273.5}, "class_id": 0, "box_caption": "plate_cold 0.001", "scores": {"class_score": 0.0012521743774414062}, "domain": "pixel"}, {"position": {"minX": 623.5, "minY": 302.0, "maxX": 667.5, "maxY": 385.5}, "class_id": 0, "box_caption": "plate_cold 0.001", "scores": {"class_score": 0.0012454986572265625}, "domain": "pixel"}, {"position": {"minX": 23.015625, "minY": 91.875, "maxX": 81.75, "maxY": 121.75}, "class_id": 0, "box_caption": "plate_cold 0.001", "scores": {"class_score": 0.0011997222900390625}, "domain": "pixel"}, {"position": {"minX": -34.375, "minY": 150.75, "maxX": 40.25, "maxY": 254.25}, "class_id": 0, "box_caption": "plate_cold 0.001", "scores": {"class_score": 0.0011396408081054688}, "domain": "pixel"}], "class_labels": {"0": "plate_cold"}}