{"box_data": [{"position": {"minX": 578.0, "minY": 197.75, "maxX": 643.0, "maxY": 240.5}, "class_id": 0, "box_caption": "plate_cold 0.033", "scores": {"class_score": 0.033355712890625}, "domain": "pixel"}, {"position": {"minX": -43.0, "minY": 223.125, "maxX": 607.5, "maxY": 246.375}, "class_id": 0, "box_caption": "plate_cold 0.028", "scores": {"class_score": 0.0279693603515625}, "domain": "pixel"}, {"position": {"minX": 252.5, "minY": 112.875, "maxX": 631.5, "maxY": 135.875}, "class_id": 0, "box_caption": "plate_cold 0.020", "scores": {"class_score": 0.019744873046875}, "domain": "pixel"}, {"position": {"minX": 56.125, "minY": 217.375, "maxX": 521.0, "maxY": 236.875}, "class_id": 0, "box_caption": "plate_cold 0.018", "scores": {"class_score": 0.0182342529296875}, "domain": "pixel"}, {"position": {"minX": 254.25, "minY": 219.75, "maxX": 530.0, "maxY": 234.25}, "class_id": 0, "box_caption": "plate_cold 0.018", "scores": {"class_score": 0.0177459716796875}, "domain": "pixel"}, {"position": {"minX": 34.25, "minY": 171.375, "maxX": 559.0, "maxY": 189.375}, "class_id": 0, "box_caption": "plate_cold 0.018", "scores": {"class_score": 0.0177154541015625}, "domain": "pixel"}, {"position": {"minX": -55.0, "minY": 229.125, "maxX": 614.5, "maxY": 261.75}, "class_id": 0, "box_caption": "plate_cold 0.017", "scores": {"class_score": 0.017242431640625}, "domain": "pixel"}, {"position": {"minX": -39.0, "minY": 102.0, "maxX": 572.5, "maxY": 143.375}, "class_id": 0, "box_caption": "plate_cold 0.017", "scores": {"class_score": 0.017181396484375}, "domain": "pixel"}, {"position": {"minX": 133.5, "minY": 110.0625, "maxX": 670.5, "maxY": 138.25}, "class_id": 0, "box_caption": "plate_cold 0.015", "scores": {"class_score": 0.01531219482421875}, "domain": "pixel"}, {"position": {"minX": -8.25, "minY": 145.5, "maxX": 539.0, "maxY": 166.75}, "class_id": 0, "box_caption": "plate_cold 0.014", "scores": {"class_score": 0.013916015625}, "domain": "pixel"}, {"position": {"minX": 574.5, "minY": 205.0, "maxX": 648.5, "maxY": 232.75}, "class_id": 0, "box_caption": "plate_cold 0.014", "scores": {"class_score": 0.01351165771484375}, "domain": "pixel"}, {"position": {"minX": 542.5, "minY": 203.5, "maxX": 664.5, "maxY": 239.25}, "class_id": 0, "box_caption": "plate_cold 0.013", "scores": {"class_score": 0.013275146484375}, "domain": "pixel"}, {"position": {"minX": 26.25, "minY": 215.875, "maxX": 550.0, "maxY": 223.875}, "class_id": 0, "box_caption": "plate_cold 0.013", "scores": {"class_score": 0.01326751708984375}, "domain": "pixel"}, {"position": {"minX": 84.25, "minY": 154.0, "maxX": 590.0, "maxY": 174.25}, "class_id": 0, "box_caption": "plate_cold 0.013", "scores": {"class_score": 0.012542724609375}, "domain": "pixel"}, {"position": {"minX": 180.5, "minY": 148.0, "maxX": 621.5, "maxY": 165.75}, "class_id": 0, "box_caption": "plate_cold 0.012", "scores": {"class_score": 0.01194000244140625}, "domain": "pixel"}, {"position": {"minX": -16.875, "minY": 110.875, "maxX": 482.0, "maxY": 137.875}, "class_id": 0, "box_caption": "plate_cold 0.012", "scores": {"class_score": 0.0117034912109375}, "domain": "pixel"}, {"position": {"minX": 122.625, "minY": 224.375, "maxX": 566.5, "maxY": 244.125}, "class_id": 0, "box_caption": "plate_cold 0.012", "scores": {"class_score": 0.0117034912109375}, "domain": "pixel"}, {"position": {"minX": 281.25, "minY": 224.75, "maxX": 513.5, "maxY": 233.5}, "class_id": 0, "box_caption": "plate_cold 0.011", "scores": {"class_score": 0.01145172119140625}, "domain": "pixel"}, {"position": {"minX": 123.5, "minY": 259.0, "maxX": 235.5, "maxY": 276.5}, "class_id": 0, "box_caption": "plate_cold 0.011", "scores": {"class_score": 0.010986328125}, "domain": "pixel"}, {"position": {"minX": 4.75, "minY": 132.0, "maxX": 542.0, "maxY": 161.25}, "class_id": 0, "box_caption": "plate_cold 0.011", "scores": {"class_score": 0.0108184814453125}, "domain": "pixel"}, {"position": {"minX": -96.5, "minY": 116.6875, "maxX": 625.5, "maxY": 145.875}, "class_id": 0, "box_caption": "plate_cold 0.011", "scores": {"class_score": 0.01071929931640625}, "domain": "pixel"}, {"position": {"minX": 11.75, "minY": 218.5, "maxX": 522.0, "maxY": 252.5}, "class_id": 0, "box_caption": "plate_cold 0.011", "scores": {"class_score": 0.0106201171875}, "domain": "pixel"}, {"position": {"minX": 236.875, "minY": 216.5, "maxX": 546.5, "maxY": 225.0}, "class_id": 0, "box_caption": "plate_cold 0.010", "scores": {"class_score": 0.01036834716796875}, "domain": "pixel"}, {"position": {"minX": 196.875, "minY": 171.625, "maxX": 588.0, "maxY": 187.375}, "class_id": 0, "box_caption": "plate_cold 0.010", "scores": {"class_score": 0.01023101806640625}, "domain": "pixel"}, {"position": {"minX": 60.0, "minY": 178.0, "maxX": 516.5, "maxY": 196.75}, "class_id": 0, "box_caption": "plate_cold 0.010", "scores": {"class_score": 0.01003265380859375}, "domain": "pixel"}, {"position": {"minX": 198.0, "minY": 156.0, "maxX": 604.0, "maxY": 171.5}, "class_id": 0, "box_caption": "plate_cold 0.010", "scores": {"class_score": 0.01000213623046875}, "domain": "pixel"}, {"position": {"minX": 235.875, "minY": 108.1875, "maxX": 644.5, "maxY": 126.6875}, "class_id": 0, "box_caption": "plate_cold 0.010", "scores": {"class_score": 0.0097808837890625}, "domain": "pixel"}, {"position": {"minX": -1.25, "minY": 149.5, "maxX": 564.0, "maxY": 181.75}, "class_id": 0, "box_caption": "plate_cold 0.009", "scores": {"class_score": 0.00934600830078125}, "domain": "pixel"}, {"position": {"minX": 243.25, "minY": 227.625, "maxX": 541.0, "maxY": 240.375}, "class_id": 0, "box_caption": "plate_cold 0.009", "scores": {"class_score": 0.00930023193359375}, "domain": "pixel"}, {"position": {"minX": -29.375, "minY": 104.75, "maxX": 494.0, "maxY": 128.875}, "class_id": 0, "box_caption": "plate_cold 0.009", "scores": {"class_score": 0.00928497314453125}, "domain": "pixel"}, {"position": {"minX": -59.25, "minY": 209.0, "maxX": 622.0, "maxY": 230.0}, "class_id": 0, "box_caption": "plate_cold 0.009", "scores": {"class_score": 0.00899505615234375}, "domain": "pixel"}, {"position": {"minX": -51.5, "minY": 109.5, "maxX": 707.5, "maxY": 169.75}, "class_id": 0, "box_caption": "plate_cold 0.009", "scores": {"class_score": 0.0089569091796875}, "domain": "pixel"}, {"position": {"minX": -43.75, "minY": 210.375, "maxX": 696.0, "maxY": 264.25}, "class_id": 0, "box_caption": "plate_cold 0.009", "scores": {"class_score": 0.00888824462890625}, "domain": "pixel"}, {"position": {"minX": 9.75, "minY": 156.625, "maxX": 486.5, "maxY": 171.375}, "class_id": 0, "box_caption": "plate_cold 0.009", "scores": {"class_score": 0.00887298583984375}, "domain": "pixel"}, {"position": {"minX": 567.0, "minY": 202.25, "maxX": 639.0, "maxY": 250.5}, "class_id": 0, "box_caption": "plate_cold 0.009", "scores": {"class_score": 0.0088348388671875}, "domain": "pixel"}, {"position": {"minX": 23.8125, "minY": 230.125, "maxX": 226.75, "maxY": 240.875}, "class_id": 0, "box_caption": "plate_cold 0.009", "scores": {"class_score": 0.0087432861328125}, "domain": "pixel"}, {"position": {"minX": -15.75, "minY": 135.25, "maxX": 581.0, "maxY": 172.5}, "class_id": 0, "box_caption": "plate_cold 0.009", "scores": {"class_score": 0.00865936279296875}, "domain": "pixel"}, {"position": {"minX": 1.25, "minY": 174.75, "maxX": 317.75, "maxY": 185.75}, "class_id": 0, "box_caption": "plate_cold 0.009", "scores": {"class_score": 0.00853729248046875}, "domain": "pixel"}, {"position": {"minX": 321.5, "minY": 221.125, "maxX": 495.0, "maxY": 234.875}, "class_id": 0, "box_caption": "plate_cold 0.008", "scores": {"class_score": 0.008270263671875}, "domain": "pixel"}, {"position": {"minX": 18.625, "minY": 173.75, "maxX": 428.0, "maxY": 187.0}, "class_id": 0, "box_caption": "plate_cold 0.008", "scores": {"class_score": 0.008087158203125}, "domain": "pixel"}, {"position": {"minX": -22.25, "minY": 174.75, "maxX": 586.0, "maxY": 194.75}, "class_id": 0, "box_caption": "plate_cold 0.008", "scores": {"class_score": 0.008087158203125}, "domain": "pixel"}, {"position": {"minX": 106.0, "minY": 104.125, "maxX": 695.0, "maxY": 129.25}, "class_id": 0, "box_caption": "plate_cold 0.008", "scores": {"class_score": 0.007801055908203125}, "domain": "pixel"}, {"position": {"minX": 281.0, "minY": 230.75, "maxX": 510.0, "maxY": 239.5}, "class_id": 0, "box_caption": "plate_cold 0.008", "scores": {"class_score": 0.0077972412109375}, "domain": "pixel"}, {"position": {"minX": 41.0, "minY": 202.5, "maxX": 555.0, "maxY": 236.75}, "class_id": 0, "box_caption": "plate_cold 0.007", "scores": {"class_score": 0.0074920654296875}, "domain": "pixel"}, {"position": {"minX": -31.75, "minY": 215.0, "maxX": 591.0, "maxY": 282.75}, "class_id": 0, "box_caption": "plate_cold 0.007", "scores": {"class_score": 0.0074462890625}, "domain": "pixel"}, {"position": {"minX": -19.5, "minY": 113.875, "maxX": 341.25, "maxY": 135.125}, "class_id": 0, "box_caption": "plate_cold 0.007", "scores": {"class_score": 0.00724029541015625}, "domain": "pixel"}, {"position": {"minX": 19.5, "minY": 149.0, "maxX": 413.5, "maxY": 165.0}, "class_id": 0, "box_caption": "plate_cold 0.007", "scores": {"class_score": 0.00719451904296875}, "domain": "pixel"}, {"position": {"minX": 12.5625, "minY": 222.75, "maxX": 226.25, "maxY": 233.0}, "class_id": 0, "box_caption": "plate_cold 0.007", "scores": {"class_score": 0.00716400146484375}, "domain": "pixel"}, {"position": {"minX": 59.5, "minY": 212.5, "maxX": 537.5, "maxY": 229.75}, "class_id": 0, "box_caption": "plate_cold 0.007", "scores": {"class_score": 0.00714874267578125}, "domain": "pixel"}, {"position": {"minX": 28.125, "minY": 224.875, "maxX": 435.5, "maxY": 244.125}, "class_id": 0, "box_caption": "plate_cold 0.007", "scores": {"class_score": 0.007114410400390625}, "domain": "pixel"}, {"position": {"minX": 0.5, "minY": 86.75, "maxX": 665.0, "maxY": 154.375}, "class_id": 0, "box_caption": "plate_cold 0.007", "scores": {"class_score": 0.006855010986328125}, "domain": "pixel"}, {"position": {"minX": 297.75, "minY": 123.1875, "maxX": 584.0, "maxY": 139.25}, "class_id": 0, "box_caption": "plate_cold 0.007", "scores": {"class_score": 0.0068206787109375}, "domain": "pixel"}, {"position": {"minX": 183.625, "minY": 122.125, "maxX": 618.5, "maxY": 140.875}, "class_id": 0, "box_caption": "plate_cold 0.007", "scores": {"class_score": 0.00658416748046875}, "domain": "pixel"}, {"position": {"minX": 276.0, "minY": 218.0, "maxX": 523.0, "maxY": 224.0}, "class_id": 0, "box_caption": "plate_cold 0.006", "scores": {"class_score": 0.006435394287109375}, "domain": "pixel"}, {"position": {"minX": -30.5, "minY": 233.125, "maxX": 543.0, "maxY": 254.375}, "class_id": 0, "box_caption": "plate_cold 0.006", "scores": {"class_score": 0.006244659423828125}, "domain": "pixel"}, {"position": {"minX": 19.625, "minY": 219.875, "maxX": 299.0, "maxY": 233.375}, "class_id": 0, "box_caption": "plate_cold 0.006", "scores": {"class_score": 0.00623321533203125}, "domain": "pixel"}, {"position": {"minX": 27.625, "minY": 219.0, "maxX": 419.0, "maxY": 234.5}, "class_id": 0, "box_caption": "plate_cold 0.006", "scores": {"class_score": 0.006183624267578125}, "domain": "pixel"}, {"position": {"minX": 13.5, "minY": 131.5, "maxX": 307.0, "maxY": 162.75}, "class_id": 0, "box_caption": "plate_cold 0.006", "scores": {"class_score": 0.00617218017578125}, "domain": "pixel"}, {"position": {"minX": 71.0, "minY": 161.125, "maxX": 586.5, "maxY": 180.125}, "class_id": 0, "box_caption": "plate_cold 0.006", "scores": {"class_score": 0.006061553955078125}, "domain": "pixel"}, {"position": {"minX": 185.125, "minY": 131.5, "maxX": 616.0, "maxY": 162.25}, "class_id": 0, "box_caption": "plate_cold 0.006", "scores": {"class_score": 0.006053924560546875}, "domain": "pixel"}, {"position": {"minX": 271.5, "minY": 150.375, "maxX": 593.5, "maxY": 163.875}, "class_id": 0, "box_caption": "plate_cold 0.006", "scores": {"class_score": 0.00601959228515625}, "domain": "pixel"}, {"position": {"minX": 24.75, "minY": 204.625, "maxX": 550.0, "maxY": 216.875}, "class_id": 0, "box_caption": "plate_cold 0.006", "scores": {"class_score": 0.005970001220703125}, "domain": "pixel"}, {"position": {"minX": -65.75, "minY": 178.0, "maxX": 721.0, "maxY": 237.25}, "class_id": 0, "box_caption": "plate_cold 0.006", "scores": {"class_score": 0.005954742431640625}, "domain": "pixel"}, {"position": {"minX": -51.25, "minY": 142.5, "maxX": 707.0, "maxY": 199.25}, "class_id": 0, "box_caption": "plate_cold 0.006", "scores": {"class_score": 0.00592041015625}, "domain": "pixel"}, {"position": {"minX": -12.875, "minY": 109.625, "maxX": 317.5, "maxY": 126.75}, "class_id": 0, "box_caption": "plate_cold 0.006", "scores": {"class_score": 0.00588226318359375}, "domain": "pixel"}, {"position": {"minX": -8.875, "minY": 150.0, "maxX": 265.0, "maxY": 163.25}, "class_id": 0, "box_caption": "plate_cold 0.006", "scores": {"class_score": 0.0058135986328125}, "domain": "pixel"}, {"position": {"minX": 587.5, "minY": 193.0, "maxX": 648.5, "maxY": 232.0}, "class_id": 0, "box_caption": "plate_cold 0.006", "scores": {"class_score": 0.00579833984375}, "domain": "pixel"}, {"position": {"minX": 336.0, "minY": 169.5, "maxX": 577.5, "maxY": 187.75}, "class_id": 0, "box_caption": "plate_cold 0.006", "scores": {"class_score": 0.005748748779296875}, "domain": "pixel"}, {"position": {"minX": 6.0, "minY": 237.75, "maxX": 558.5, "maxY": 270.25}, "class_id": 0, "box_caption": "plate_cold 0.006", "scores": {"class_score": 0.00566864013671875}, "domain": "pixel"}, {"position": {"minX": 16.375, "minY": 171.875, "maxX": 514.5, "maxY": 201.375}, "class_id": 0, "box_caption": "plate_cold 0.006", "scores": {"class_score": 0.005523681640625}, "domain": "pixel"}, {"position": {"minX": -68.0, "minY": 187.125, "maxX": 630.0, "maxY": 209.125}, "class_id": 0, "box_caption": "plate_cold 0.005", "scores": {"class_score": 0.005458831787109375}, "domain": "pixel"}, {"position": {"minX": 28.25, "minY": 119.25, "maxX": 468.75, "maxY": 142.75}, "class_id": 0, "box_caption": "plate_cold 0.005", "scores": {"class_score": 0.005397796630859375}, "domain": "pixel"}, {"position": {"minX": 59.625, "minY": 250.625, "maxX": 298.5, "maxY": 271.5}, "class_id": 0, "box_caption": "plate_cold 0.005", "scores": {"class_score": 0.0052947998046875}, "domain": "pixel"}, {"position": {"minX": 137.125, "minY": 253.625, "maxX": 223.375, "maxY": 271.25}, "class_id": 0, "box_caption": "plate_cold 0.005", "scores": {"class_score": 0.00528717041015625}, "domain": "pixel"}, {"position": {"minX": 185.875, "minY": 206.25, "maxX": 596.0, "maxY": 217.5}, "class_id": 0, "box_caption": "plate_cold 0.005", "scores": {"class_score": 0.00527191162109375}, "domain": "pixel"}, {"position": {"minX": 23.5, "minY": 226.25, "maxX": 295.25, "maxY": 242.5}, "class_id": 0, "box_caption": "plate_cold 0.005", "scores": {"class_score": 0.00525665283203125}, "domain": "pixel"}, {"position": {"minX": 569.0, "minY": 201.625, "maxX": 621.0, "maxY": 238.875}, "class_id": 0, "box_caption": "plate_cold 0.005", "scores": {"class_score": 0.005054473876953125}, "domain": "pixel"}, {"position": {"minX": 28.0, "minY": 183.125, "maxX": 534.5, "maxY": 215.375}, "class_id": 0, "box_caption": "plate_cold 0.005", "scores": {"class_score": 0.00501251220703125}, "domain": "pixel"}, {"position": {"minX": 274.0, "minY": 214.875, "maxX": 518.5, "maxY": 226.875}, "class_id": 0, "box_caption": "plate_cold 0.005", "scores": {"class_score": 0.0047607421875}, "domain": "pixel"}, {"position": {"minX": 335.5, "minY": 113.875, "maxX": 585.0, "maxY": 138.5}, "class_id": 0, "box_caption": "plate_cold 0.005", "scores": {"class_score": 0.0045928955078125}, "domain": "pixel"}, {"position": {"minX": -1.8125, "minY": 152.125, "maxX": 193.25, "maxY": 162.125}, "class_id": 0, "box_caption": "plate_cold 0.005", "scores": {"class_score": 0.00457763671875}, "domain": "pixel"}, {"position": {"minX": 225.125, "minY": 178.75, "maxX": 543.0, "maxY": 195.5}, "class_id": 0, "box_caption": "plate_cold 0.004", "scores": {"class_score": 0.004398345947265625}, "domain": "pixel"}, {"position": {"minX": 209.875, "minY": 222.375, "maxX": 486.5, "maxY": 235.625}, "class_id": 0, "box_caption": "plate_cold 0.004", "scores": {"class_score": 0.004364013671875}, "domain": "pixel"}, {"position": {"minX": 3.75, "minY": 191.75, "maxX": 570.0, "maxY": 201.25}, "class_id": 0, "box_caption": "plate_cold 0.004", "scores": {"class_score": 0.0043487548828125}, "domain": "pixel"}, {"position": {"minX": 32.125, "minY": 215.125, "maxX": 302.0, "maxY": 223.625}, "class_id": 0, "box_caption": "plate_cold 0.004", "scores": {"class_score": 0.004302978515625}, "domain": "pixel"}, {"position": {"minX": 16.0, "minY": 92.125, "maxX": 514.0, "maxY": 121.75}, "class_id": 0, "box_caption": "plate_cold 0.004", "scores": {"class_score": 0.004261016845703125}, "domain": "pixel"}, {"position": {"minX": 128.25, "minY": 145.625, "maxX": 585.0, "maxY": 171.625}, "class_id": 0, "box_caption": "plate_cold 0.004", "scores": {"class_score": 0.004161834716796875}, "domain": "pixel"}, {"position": {"minX": 17.0, "minY": 111.3125, "maxX": 675.0, "maxY": 153.0}, "class_id": 0, "box_caption": "plate_cold 0.004", "scores": {"class_score": 0.004146575927734375}, "domain": "pixel"}, {"position": {"minX": 212.125, "minY": 228.625, "maxX": 482.5, "maxY": 242.375}, "class_id": 0, "box_caption": "plate_cold 0.004", "scores": {"class_score": 0.003986358642578125}, "domain": "pixel"}, {"position": {"minX": 25.3125, "minY": 220.375, "maxX": 210.25, "maxY": 230.625}, "class_id": 0, "box_caption": "plate_cold 0.004", "scores": {"class_score": 0.0039825439453125}, "domain": "pixel"}, {"position": {"minX": 300.5, "minY": 133.875, "maxX": 596.5, "maxY": 160.625}, "class_id": 0, "box_caption": "plate_cold 0.004", "scores": {"class_score": 0.00391387939453125}, "domain": "pixel"}, {"position": {"minX": 28.75, "minY": 197.875, "maxX": 563.0, "maxY": 209.625}, "class_id": 0, "box_caption": "plate_cold 0.004", "scores": {"class_score": 0.0038967132568359375}, "domain": "pixel"}, {"position": {"minX": 19.25, "minY": 215.875, "maxX": 219.25, "maxY": 224.375}, "class_id": 0, "box_caption": "plate_cold 0.004", "scores": {"class_score": 0.00388336181640625}, "domain": "pixel"}, {"position": {"minX": 340.5, "minY": 178.5, "maxX": 580.5, "maxY": 188.5}, "class_id": 0, "box_caption": "plate_cold 0.004", "scores": {"class_score": 0.003849029541015625}, "domain": "pixel"}, {"position": {"minX": -12.0, "minY": 130.625, "maxX": 558.0, "maxY": 146.625}, "class_id": 0, "box_caption": "plate_cold 0.004", "scores": {"class_score": 0.0038242340087890625}, "domain": "pixel"}, {"position": {"minX": 220.0, "minY": 211.5, "maxX": 557.5, "maxY": 228.5}, "class_id": 0, "box_caption": "plate_cold 0.004", "scores": {"class_score": 0.003818511962890625}, "domain": "pixel"}, {"position": {"minX": 47.0, "minY": 97.125, "maxX": 416.25, "maxY": 117.75}, "class_id": 0, "box_caption": "plate_cold 0.004", "scores": {"class_score": 0.003810882568359375}, "domain": "pixel"}, {"position": {"minX": 368.0, "minY": 116.5, "maxX": 626.0, "maxY": 135.5}, "class_id": 0, "box_caption": "plate_cold 0.004", "scores": {"class_score": 0.003704071044921875}, "domain": "pixel"}, {"position": {"minX": 148.625, "minY": 220.375, "maxX": 435.5, "maxY": 236.125}, "class_id": 0, "box_caption": "plate_cold 0.004", "scores": {"class_score": 0.003665924072265625}, "domain": "pixel"}, {"position": {"minX": 44.5, "minY": 177.875, "maxX": 282.5, "maxY": 187.625}, "class_id": 0, "box_caption": "plate_cold 0.004", "scores": {"class_score": 0.0036373138427734375}, "domain": "pixel"}, {"position": {"minX": 407.5, "minY": 172.75, "maxX": 600.0, "maxY": 189.25}, "class_id": 0, "box_caption": "plate_cold 0.004", "scores": {"class_score": 0.0036296844482421875}, "domain": "pixel"}, {"position": {"minX": 111.25, "minY": 175.25, "maxX": 391.5, "maxY": 189.0}, "class_id": 0, "box_caption": "plate_cold 0.004", "scores": {"class_score": 0.003627777099609375}, "domain": "pixel"}, {"position": {"minX": 68.375, "minY": 180.25, "maxX": 394.0, "maxY": 194.5}, "class_id": 0, "box_caption": "plate_cold 0.004", "scores": {"class_score": 0.003604888916015625}, "domain": "pixel"}, {"position": {"minX": 228.0, "minY": 151.75, "maxX": 580.0, "maxY": 178.25}, "class_id": 0, "box_caption": "plate_cold 0.004", "scores": {"class_score": 0.003536224365234375}, "domain": "pixel"}, {"position": {"minX": 314.5, "minY": 158.0, "maxX": 581.5, "maxY": 171.5}, "class_id": 0, "box_caption": "plate_cold 0.004", "scores": {"class_score": 0.0035247802734375}, "domain": "pixel"}, {"position": {"minX": 40.75, "minY": 181.125, "maxX": 294.0, "maxY": 194.375}, "class_id": 0, "box_caption": "plate_cold 0.004", "scores": {"class_score": 0.0035228729248046875}, "domain": "pixel"}, {"position": {"minX": -25.25, "minY": 118.375, "maxX": 587.0, "maxY": 190.625}, "class_id": 0, "box_caption": "plate_cold 0.004", "scores": {"class_score": 0.0035076141357421875}, "domain": "pixel"}, {"position": {"minX": -12.0, "minY": 233.125, "maxX": 568.0, "maxY": 295.5}, "class_id": 0, "box_caption": "plate_cold 0.003", "scores": {"class_score": 0.0034809112548828125}, "domain": "pixel"}, {"position": {"minX": -31.546875, "minY": 269.0, "maxX": 53.375, "maxY": 382.5}, "class_id": 0, "box_caption": "plate_cold 0.003", "scores": {"class_score": 0.0034637451171875}, "domain": "pixel"}, {"position": {"minX": 297.5, "minY": 221.0, "maxX": 511.5, "maxY": 230.5}, "class_id": 0, "box_caption": "plate_cold 0.003", "scores": {"class_score": 0.0034332275390625}, "domain": "pixel"}, {"position": {"minX": 332.5, "minY": 110.5625, "maxX": 628.0, "maxY": 125.0625}, "class_id": 0, "box_caption": "plate_cold 0.003", "scores": {"class_score": 0.0034275054931640625}, "domain": "pixel"}, {"position": {"minX": 409.0, "minY": 179.625, "maxX": 608.5, "maxY": 188.125}, "class_id": 0, "box_caption": "plate_cold 0.003", "scores": {"class_score": 0.00342559814453125}, "domain": "pixel"}, {"position": {"minX": 197.25, "minY": 172.875, "maxX": 482.25, "maxY": 191.125}, "class_id": 0, "box_caption": "plate_cold 0.003", "scores": {"class_score": 0.003368377685546875}, "domain": "pixel"}, {"position": {"minX": 5.5, "minY": 140.125, "maxX": 651.0, "maxY": 164.875}, "class_id": 0, "box_caption": "plate_cold 0.003", "scores": {"class_score": 0.0033588409423828125}, "domain": "pixel"}, {"position": {"minX": -9.9375, "minY": 176.25, "maxX": 200.25, "maxY": 185.25}, "class_id": 0, "box_caption": "plate_cold 0.003", "scores": {"class_score": 0.003353118896484375}, "domain": "pixel"}, {"position": {"minX": 278.5, "minY": 175.125, "maxX": 529.0, "maxY": 189.625}, "class_id": 0, "box_caption": "plate_cold 0.003", "scores": {"class_score": 0.0033168792724609375}, "domain": "pixel"}, {"position": {"minX": 58.25, "minY": 202.25, "maxX": 522.0, "maxY": 222.5}, "class_id": 0, "box_caption": "plate_cold 0.003", "scores": {"class_score": 0.0033111572265625}, "domain": "pixel"}, {"position": {"minX": 20.125, "minY": 227.625, "maxX": 248.625, "maxY": 238.875}, "class_id": 0, "box_caption": "plate_cold 0.003", "scores": {"class_score": 0.0032806396484375}, "domain": "pixel"}, {"position": {"minX": -109.25, "minY": -25.984375, "maxX": 662.0, "maxY": 86.3125}, "class_id": 0, "box_caption": "plate_cold 0.003", "scores": {"class_score": 0.0032444000244140625}, "domain": "pixel"}, {"position": {"minX": 90.5, "minY": 229.5, "maxX": 349.0, "maxY": 240.75}, "class_id": 0, "box_caption": "plate_cold 0.003", "scores": {"class_score": 0.003231048583984375}, "domain": "pixel"}, {"position": {"minX": -31.6875, "minY": 222.625, "maxX": 273.0, "maxY": 246.625}, "class_id": 0, "box_caption": "plate_cold 0.003", "scores": {"class_score": 0.0032291412353515625}, "domain": "pixel"}, {"position": {"minX": 111.875, "minY": 250.125, "maxX": 250.875, "maxY": 270.25}, "class_id": 0, "box_caption": "plate_cold 0.003", "scores": {"class_score": 0.0032253265380859375}, "domain": "pixel"}, {"position": {"minX": 18.0, "minY": 227.875, "maxX": 169.5, "maxY": 241.375}, "class_id": 0, "box_caption": "plate_cold 0.003", "scores": {"class_score": 0.0031948089599609375}, "domain": "pixel"}, {"position": {"minX": -13.3125, "minY": 134.625, "maxX": 204.25, "maxY": 161.125}, "class_id": 0, "box_caption": "plate_cold 0.003", "scores": {"class_score": 0.00315093994140625}, "domain": "pixel"}, {"position": {"minX": 54.5625, "minY": 230.875, "maxX": 290.25, "maxY": 240.625}, "class_id": 0, "box_caption": "plate_cold 0.003", "scores": {"class_score": 0.003116607666015625}, "domain": "pixel"}, {"position": {"minX": -18.875, "minY": 158.0, "maxX": 320.5, "maxY": 173.5}, "class_id": 0, "box_caption": "plate_cold 0.003", "scores": {"class_score": 0.00311279296875}, "domain": "pixel"}, {"position": {"minX": 163.5, "minY": 226.0, "maxX": 453.0, "maxY": 245.0}, "class_id": 0, "box_caption": "plate_cold 0.003", "scores": {"class_score": 0.003101348876953125}, "domain": "pixel"}, {"position": {"minX": 478.0, "minY": 267.25, "maxX": 555.0, "maxY": 284.25}, "class_id": 0, "box_caption": "plate_cold 0.003", "scores": {"class_score": 0.0030975341796875}, "domain": "pixel"}, {"position": {"minX": 351.5, "minY": 138.0, "maxX": 624.5, "maxY": 158.5}, "class_id": 0, "box_caption": "plate_cold 0.003", "scores": {"class_score": 0.0030498504638671875}, "domain": "pixel"}, {"position": {"minX": 91.5, "minY": 112.25, "maxX": 377.75, "maxY": 137.625}, "class_id": 0, "box_caption": "plate_cold 0.003", "scores": {"class_score": 0.0030059814453125}, "domain": "pixel"}, {"position": {"minX": 207.25, "minY": 153.0, "maxX": 485.75, "maxY": 175.25}, "class_id": 0, "box_caption": "plate_cold 0.003", "scores": {"class_score": 0.0029354095458984375}, "domain": "pixel"}, {"position": {"minX": 34.75, "minY": 152.625, "maxX": 437.75, "maxY": 178.375}, "class_id": 0, "box_caption": "plate_cold 0.003", "scores": {"class_score": 0.0029296875}, "domain": "pixel"}, {"position": {"minX": 313.5, "minY": 100.625, "maxX": 596.5, "maxY": 118.0}, "class_id": 0, "box_caption": "plate_cold 0.003", "scores": {"class_score": 0.00292205810546875}, "domain": "pixel"}, {"position": {"minX": 569.0, "minY": 192.5, "maxX": 662.0, "maxY": 248.75}, "class_id": 0, "box_caption": "plate_cold 0.003", "scores": {"class_score": 0.0028705596923828125}, "domain": "pixel"}, {"position": {"minX": -2.25, "minY": 161.5, "maxX": 432.5, "maxY": 179.5}, "class_id": 0, "box_caption": "plate_cold 0.003", "scores": {"class_score": 0.0028476715087890625}, "domain": "pixel"}, {"position": {"minX": 37.75, "minY": 235.0, "maxX": 393.75, "maxY": 253.0}, "class_id": 0, "box_caption": "plate_cold 0.003", "scores": {"class_score": 0.0028209686279296875}, "domain": "pixel"}, {"position": {"minX": 558.5, "minY": 213.5, "maxX": 648.5, "maxY": 238.75}, "class_id": 0, "box_caption": "plate_cold 0.003", "scores": {"class_score": 0.00281524658203125}, "domain": "pixel"}, {"position": {"minX": 46.25, "minY": 100.0625, "maxX": 288.0, "maxY": 116.8125}, "class_id": 0, "box_caption": "plate_cold 0.003", "scores": {"class_score": 0.0027942657470703125}, "domain": "pixel"}, {"position": {"minX": 111.125, "minY": 227.0, "maxX": 392.5, "maxY": 242.25}, "class_id": 0, "box_caption": "plate_cold 0.003", "scores": {"class_score": 0.002773284912109375}, "domain": "pixel"}, {"position": {"minX": -72.5, "minY": 88.9375, "maxX": 632.5, "maxY": 126.1875}, "class_id": 0, "box_caption": "plate_cold 0.003", "scores": {"class_score": 0.0027484893798828125}, "domain": "pixel"}, {"position": {"minX": 32.625, "minY": 245.25, "maxX": 305.5, "maxY": 262.5}, "class_id": 0, "box_caption": "plate_cold 0.003", "scores": {"class_score": 0.0027294158935546875}, "domain": "pixel"}, {"position": {"minX": 491.0, "minY": 180.125, "maxX": 710.0, "maxY": 253.875}, "class_id": 0, "box_caption": "plate_cold 0.003", "scores": {"class_score": 0.0027141571044921875}, "domain": "pixel"}, {"position": {"minX": -302.25, "minY": -60.71875, "maxX": 358.25, "maxY": 89.75}, "class_id": 0, "box_caption": "plate_cold 0.003", "scores": {"class_score": 0.002712249755859375}, "domain": "pixel"}, {"position": {"minX": 115.75, "minY": 145.875, "maxX": 401.25, "maxY": 169.625}, "class_id": 0, "box_caption": "plate_cold 0.003", "scores": {"class_score": 0.0026721954345703125}, "domain": "pixel"}, {"position": {"minX": 253.25, "minY": 258.5, "maxX": 1058.0, "maxY": 466.5}, "class_id": 0, "box_caption": "plate_cold 0.003", "scores": {"class_score": 0.002666473388671875}, "domain": "pixel"}, {"position": {"minX": 57.0, "minY": 223.5, "maxX": 288.0, "maxY": 233.25}, "class_id": 0, "box_caption": "plate_cold 0.003", "scores": {"class_score": 0.002658843994140625}, "domain": "pixel"}, {"position": {"minX": 96.6875, "minY": 177.25, "maxX": 342.25, "maxY": 187.5}, "class_id": 0, "box_caption": "plate_cold 0.003", "scores": {"class_score": 0.0026569366455078125}, "domain": "pixel"}, {"position": {"minX": 329.0, "minY": 229.0, "maxX": 503.5, "maxY": 241.0}, "class_id": 0, "box_caption": "plate_cold 0.003", "scores": {"class_score": 0.0026531219482421875}, "domain": "pixel"}, {"position": {"minX": 1.4375, "minY": 150.5, "maxX": 200.25, "maxY": 166.5}, "class_id": 0, "box_caption": "plate_cold 0.003", "scores": {"class_score": 0.00263214111328125}, "domain": "pixel"}, {"position": {"minX": 187.5, "minY": 129.25, "maxX": 614.0, "maxY": 148.25}, "class_id": 0, "box_caption": "plate_cold 0.003", "scores": {"class_score": 0.00263214111328125}, "domain": "pixel"}, {"position": {"minX": 77.0, "minY": 258.25, "maxX": 264.5, "maxY": 276.75}, "class_id": 0, "box_caption": "plate_cold 0.003", "scores": {"class_score": 0.002567291259765625}, "domain": "pixel"}, {"position": {"minX": 227.5, "minY": 295.0, "maxX": 919.5, "maxY": 333.5}, "class_id": 0, "box_caption": "plate_cold 0.003", "scores": {"class_score": 0.002536773681640625}, "domain": "pixel"}, {"position": {"minX": -81.25, "minY": 143.875, "maxX": 361.0, "maxY": 166.125}, "class_id": 0, "box_caption": "plate_cold 0.003", "scores": {"class_score": 0.0025272369384765625}, "domain": "pixel"}, {"position": {"minX": 269.0, "minY": 147.25, "maxX": 538.5, "maxY": 169.25}, "class_id": 0, "box_caption": "plate_cold 0.002", "scores": {"class_score": 0.0024967193603515625}, "domain": "pixel"}, {"position": {"minX": 101.75, "minY": 222.625, "maxX": 370.0, "maxY": 233.875}, "class_id": 0, "box_caption": "plate_cold 0.002", "scores": {"class_score": 0.0024814605712890625}, "domain": "pixel"}, {"position": {"minX": -16.5, "minY": 183.0, "maxX": 609.5, "maxY": 259.25}, "class_id": 0, "box_caption": "plate_cold 0.002", "scores": {"class_score": 0.0024623870849609375}, "domain": "pixel"}, {"position": {"minX": 374.0, "minY": 157.5, "maxX": 619.0, "maxY": 175.5}, "class_id": 0, "box_caption": "plate_cold 0.002", "scores": {"class_score": 0.002460479736328125}, "domain": "pixel"}, {"position": {"minX": 39.75, "minY": 57.25, "maxX": 633.0, "maxY": 181.25}, "class_id": 0, "box_caption": "plate_cold 0.002", "scores": {"class_score": 0.0024433135986328125}, "domain": "pixel"}, {"position": {"minX": -17.1875, "minY": 115.875, "maxX": 225.5, "maxY": 134.75}, "class_id": 0, "box_caption": "plate_cold 0.002", "scores": {"class_score": 0.002429962158203125}, "domain": "pixel"}, {"position": {"minX": 318.5, "minY": 108.5625, "maxX": 569.5, "maxY": 131.75}, "class_id": 0, "box_caption": "plate_cold 0.002", "scores": {"class_score": 0.00240325927734375}, "domain": "pixel"}, {"position": {"minX": 4.25, "minY": 121.0625, "maxX": 315.75, "maxY": 144.0}, "class_id": 0, "box_caption": "plate_cold 0.002", "scores": {"class_score": 0.00240325927734375}, "domain": "pixel"}, {"position": {"minX": 130.75, "minY": 228.75, "maxX": 418.25, "maxY": 258.75}, "class_id": 0, "box_caption": "plate_cold 0.002", "scores": {"class_score": 0.002399444580078125}, "domain": "pixel"}, {"position": {"minX": -81.25, "minY": 265.0, "maxX": 607.0, "maxY": 389.5}, "class_id": 0, "box_caption": "plate_cold 0.002", "scores": {"class_score": 0.002353668212890625}, "domain": "pixel"}, {"position": {"minX": 413.25, "minY": 303.5, "maxX": 896.0, "maxY": 415.0}, "class_id": 0, "box_caption": "plate_cold 0.002", "scores": {"class_score": 0.00234222412109375}, "domain": "pixel"}, {"position": {"minX": -5.125, "minY": 206.125, "maxX": 338.0, "maxY": 216.375}, "class_id": 0, "box_caption": "plate_cold 0.002", "scores": {"class_score": 0.002307891845703125}, "domain": "pixel"}, {"position": {"minX": 355.5, "minY": 152.75, "maxX": 620.5, "maxY": 163.5}, "class_id": 0, "box_caption": "plate_cold 0.002", "scores": {"class_score": 0.0022754669189453125}, "domain": "pixel"}, {"position": {"minX": 187.0, "minY": 234.25, "maxX": 582.5, "maxY": 253.5}, "class_id": 0, "box_caption": "plate_cold 0.002", "scores": {"class_score": 0.002269744873046875}, "domain": "pixel"}, {"position": {"minX": 368.5, "minY": 164.25, "maxX": 624.5, "maxY": 181.0}, "class_id": 0, "box_caption": "plate_cold 0.002", "scores": {"class_score": 0.002262115478515625}, "domain": "pixel"}, {"position": {"minX": -235.625, "minY": 169.625, "maxX": 481.5, "maxY": 559.5}, "class_id": 0, "box_caption": "plate_cold 0.002", "scores": {"class_score": 0.0022449493408203125}, "domain": "pixel"}, {"position": {"minX": 44.625, "minY": 148.875, "maxX": 296.5, "maxY": 168.375}, "class_id": 0, "box_caption": "plate_cold 0.002", "scores": {"class_score": 0.0022220611572265625}, "domain": "pixel"}, {"position": {"minX": 2.0, "minY": 189.75, "maxX": 517.5, "maxY": 207.5}, "class_id": 0, "box_caption": "plate_cold 0.002", "scores": {"class_score": 0.00222015380859375}, "domain": "pixel"}, {"position": {"minX": 117.875, "minY": -55.28125, "maxX": 438.5, "maxY": 108.0}, "class_id": 0, "box_caption": "plate_cold 0.002", "scores": {"class_score": 0.002216339111328125}, "domain": "pixel"}, {"position": {"minX": -185.25, "minY": -49.46875, "maxX": 755.0, "maxY": 152.0}, "class_id": 0, "box_caption": "plate_cold 0.002", "scores": {"class_score": 0.0022106170654296875}, "domain": "pixel"}, {"position": {"minX": 368.5, "minY": 222.125, "maxX": 507.0, "maxY": 237.125}, "class_id": 0, "box_caption": "plate_cold 0.002", "scores": {"class_score": 0.00220489501953125}, "domain": "pixel"}, {"position": {"minX": -92.375, "minY": 153.375, "maxX": 371.5, "maxY": 174.125}, "class_id": 0, "box_caption": "plate_cold 0.002", "scores": {"class_score": 0.0021724700927734375}, "domain": "pixel"}, {"position": {"minX": -2.3125, "minY": 175.375, "maxX": 157.25, "maxY": 188.875}, "class_id": 0, "box_caption": "plate_cold 0.002", "scores": {"class_score": 0.0021572113037109375}, "domain": "pixel"}, {"position": {"minX": 62.5, "minY": 193.875, "maxX": 533.5, "maxY": 217.625}, "class_id": 0, "box_caption": "plate_cold 0.002", "scores": {"class_score": 0.0021533966064453125}, "domain": "pixel"}, {"position": {"minX": 469.5, "minY": 254.125, "maxX": 562.5, "maxY": 284.75}, "class_id": 0, "box_caption": "plate_cold 0.002", "scores": {"class_score": 0.00214385986328125}, "domain": "pixel"}, {"position": {"minX": -82.5, "minY": -98.125, "maxX": 127.875, "maxY": 138.75}, "class_id": 0, "box_caption": "plate_cold 0.002", "scores": {"class_score": 0.00214385986328125}, "domain": "pixel"}, {"position": {"minX": 192.375, "minY": 97.125, "maxX": 605.5, "maxY": 118.0}, "class_id": 0, "box_caption": "plate_cold 0.002", "scores": {"class_score": 0.002140045166015625}, "domain": "pixel"}, {"position": {"minX": -17.75, "minY": 152.0, "maxX": 581.0, "maxY": 222.25}, "class_id": 0, "box_caption": "plate_cold 0.002", "scores": {"class_score": 0.0021343231201171875}, "domain": "pixel"}, {"position": {"minX": 258.5, "minY": 108.5, "maxX": 549.0, "maxY": 141.75}, "class_id": 0, "box_caption": "plate_cold 0.002", "scores": {"class_score": 0.002124786376953125}, "domain": "pixel"}, {"position": {"minX": -143.5, "minY": 280.25, "maxX": 156.5, "maxY": 389.25}, "class_id": 0, "box_caption": "plate_cold 0.002", "scores": {"class_score": 0.00208282470703125}, "domain": "pixel"}, {"position": {"minX": 133.25, "minY": 118.75, "maxX": 623.0, "maxY": 149.5}, "class_id": 0, "box_caption": "plate_cold 0.002", "scores": {"class_score": 0.0020751953125}, "domain": "pixel"}, {"position": {"minX": 70.25, "minY": -97.125, "maxX": 498.75, "maxY": 137.25}, "class_id": 0, "box_caption": "plate_cold 0.002", "scores": {"class_score": 0.0020656585693359375}, "domain": "pixel"}, {"position": {"minX": -17.125, "minY": 159.125, "maxX": 223.0, "maxY": 171.875}, "class_id": 0, "box_caption": "plate_cold 0.002", "scores": {"class_score": 0.002063751220703125}, "domain": "pixel"}, {"position": {"minX": 401.0, "minY": 182.0, "maxX": 575.0, "maxY": 194.25}, "class_id": 0, "box_caption": "plate_cold 0.002", "scores": {"class_score": 0.0020599365234375}, "domain": "pixel"}, {"position": {"minX": 9.125, "minY": 98.875, "maxX": 229.0, "maxY": 119.0}, "class_id": 0, "box_caption": "plate_cold 0.002", "scores": {"class_score": 0.002048492431640625}, "domain": "pixel"}, {"position": {"minX": 5.6875, "minY": 144.125, "maxX": 154.25, "maxY": 165.875}, "class_id": 0, "box_caption": "plate_cold 0.002", "scores": {"class_score": 0.0020389556884765625}, "domain": "pixel"}, {"position": {"minX": 139.375, "minY": 211.75, "maxX": 427.5, "maxY": 230.25}, "class_id": 0, "box_caption": "plate_cold 0.002", "scores": {"class_score": 0.002025604248046875}, "domain": "pixel"}, {"position": {"minX": 351.75, "minY": 178.0, "maxX": 544.0, "maxY": 195.75}, "class_id": 0, "box_caption": "plate_cold 0.002", "scores": {"class_score": 0.0020084381103515625}, "domain": "pixel"}, {"position": {"minX": 46.875, "minY": 157.625, "maxX": 519.0, "maxY": 185.875}, "class_id": 0, "box_caption": "plate_cold 0.002", "scores": {"class_score": 0.00199127197265625}, "domain": "pixel"}, {"position": {"minX": -55.875, "minY": 175.5, "maxX": 397.0, "maxY": 193.5}, "class_id": 0, "box_caption": "plate_cold 0.002", "scores": {"class_score": 0.0019664764404296875}, "domain": "pixel"}, {"position": {"minX": 113.875, "minY": 154.625, "maxX": 403.0, "maxY": 172.375}, "class_id": 0, "box_caption": "plate_cold 0.002", "scores": {"class_score": 0.00196075439453125}, "domain": "pixel"}, {"position": {"minX": 510.25, "minY": -58.875, "maxX": 741.0, "maxY": 122.25}, "class_id": 0, "box_caption": "plate_cold 0.002", "scores": {"class_score": 0.00196075439453125}, "domain": "pixel"}, {"position": {"minX": 87.125, "minY": 107.4375, "maxX": 367.0, "maxY": 130.5}, "class_id": 0, "box_caption": "plate_cold 0.002", "scores": {"class_score": 0.0019369125366210938}, "domain": "pixel"}, {"position": {"minX": 269.5, "minY": 163.0, "maxX": 642.0, "maxY": 179.5}, "class_id": 0, "box_caption": "plate_cold 0.002", "scores": {"class_score": 0.0019350051879882812}, "domain": "pixel"}, {"position": {"minX": -32.75, "minY": -1.0, "maxX": 587.0, "maxY": 131.625}, "class_id": 0, "box_caption": "plate_cold 0.002", "scores": {"class_score": 0.0019292831420898438}, "domain": "pixel"}, {"position": {"minX": 194.25, "minY": 218.625, "maxX": 596.0, "maxY": 238.625}, "class_id": 0, "box_caption": "plate_cold 0.002", "scores": {"class_score": 0.0019254684448242188}, "domain": "pixel"}, {"position": {"minX": 21.25, "minY": 77.625, "maxX": 538.0, "maxY": 135.25}, "class_id": 0, "box_caption": "plate_cold 0.002", "scores": {"class_score": 0.0019054412841796875}, "domain": "pixel"}, {"position": {"minX": 128.375, "minY": 106.9375, "maxX": 422.0, "maxY": 141.25}, "class_id": 0, "box_caption": "plate_cold 0.002", "scores": {"class_score": 0.0019044876098632812}, "domain": "pixel"}, {"position": {"minX": -37.875, "minY": 140.375, "maxX": 312.5, "maxY": 171.875}, "class_id": 0, "box_caption": "plate_cold 0.002", "scores": {"class_score": 0.0018968582153320312}, "domain": "pixel"}, {"position": {"minX": 150.5, "minY": 179.625, "maxX": 431.0, "maxY": 198.625}, "class_id": 0, "box_caption": "plate_cold 0.002", "scores": {"class_score": 0.0018711090087890625}, "domain": "pixel"}, {"position": {"minX": 14.75, "minY": 239.375, "maxX": 448.75, "maxY": 263.25}, "class_id": 0, "box_caption": "plate_cold 0.002", "scores": {"class_score": 0.0018472671508789062}, "domain": "pixel"}, {"position": {"minX": -38.875, "minY": 161.5, "maxX": 292.0, "maxY": 181.75}, "class_id": 0, "box_caption": "plate_cold 0.002", "scores": {"class_score": 0.001842498779296875}, "domain": "pixel"}, {"position": {"minX": 157.0, "minY": -111.6875, "maxX": 1108.0, "maxY": 151.5}, "class_id": 0, "box_caption": "plate_cold 0.002", "scores": {"class_score": 0.0018224716186523438}, "domain": "pixel"}, {"position": {"minX": 5.0, "minY": 172.25, "maxX": 168.0, "maxY": 184.75}, "class_id": 0, "box_caption": "plate_cold 0.002", "scores": {"class_score": 0.0018215179443359375}, "domain": "pixel"}, {"position": {"minX": 71.5, "minY": 97.8125, "maxX": 604.5, "maxY": 124.0625}, "class_id": 0, "box_caption": "plate_cold 0.002", "scores": {"class_score": 0.0018138885498046875}, "domain": "pixel"}, {"position": {"minX": 77.0625, "minY": 183.5, "maxX": 315.0, "maxY": 192.75}, "class_id": 0, "box_caption": "plate_cold 0.002", "scores": {"class_score": 0.0018129348754882812}, "domain": "pixel"}, {"position": {"minX": -13.125, "minY": 210.75, "maxX": 48.3125, "maxY": 223.5}, "class_id": 0, "box_caption": "plate_cold 0.002", "scores": {"class_score": 0.0018129348754882812}, "domain": "pixel"}, {"position": {"minX": -4.75, "minY": 153.75, "maxX": 276.5, "maxY": 179.25}, "class_id": 0, "box_caption": "plate_cold 0.002", "scores": {"class_score": 0.0017919540405273438}, "domain": "pixel"}, {"position": {"minX": -293.0, "minY": 234.125, "maxX": 582.5, "maxY": 493.0}, "class_id": 0, "box_caption": "plate_cold 0.002", "scores": {"class_score": 0.0017910003662109375}, "domain": "pixel"}, {"position": {"minX": 187.375, "minY": 143.0, "maxX": 474.5, "maxY": 171.75}, "class_id": 0, "box_caption": "plate_cold 0.002", "scores": {"class_score": 0.0017900466918945312}, "domain": "pixel"}, {"position": {"minX": 346.75, "minY": 216.625, "maxX": 517.0, "maxY": 226.625}, "class_id": 0, "box_caption": "plate_cold 0.002", "scores": {"class_score": 0.0017881393432617188}, "domain": "pixel"}, {"position": {"minX": -337.25, "minY": 277.5, "maxX": 408.25, "maxY": 390.5}, "class_id": 0, "box_caption": "plate_cold 0.002", "scores": {"class_score": 0.0017871856689453125}, "domain": "pixel"}, {"position": {"minX": 364.0, "minY": 125.375, "maxX": 612.0, "maxY": 140.875}, "class_id": 0, "box_caption": "plate_cold 0.002", "scores": {"class_score": 0.0017852783203125}, "domain": "pixel"}, {"position": {"minX": 463.0, "minY": 244.0, "maxX": 859.0, "maxY": 486.0}, "class_id": 0, "box_caption": "plate_cold 0.002", "scores": {"class_score": 0.001773834228515625}, "domain": "pixel"}, {"position": {"minX": 603.5, "minY": 197.625, "maxX": 648.5, "maxY": 238.625}, "class_id": 0, "box_caption": "plate_cold 0.002", "scores": {"class_score": 0.0017528533935546875}, "domain": "pixel"}, {"position": {"minX": -1.25, "minY": 145.125, "maxX": 234.75, "maxY": 161.125}, "class_id": 0, "box_caption": "plate_cold 0.002", "scores": {"class_score": 0.0017423629760742188}, "domain": "pixel"}, {"position": {"minX": 0.0, "minY": 92.8125, "maxX": 530.0, "maxY": 107.3125}, "class_id": 0, "box_caption": "plate_cold 0.002", "scores": {"class_score": 0.0017375946044921875}, "domain": "pixel"}, {"position": {"minX": 172.75, "minY": 163.5, "maxX": 850.0, "maxY": 561.5}, "class_id": 0, "box_caption": "plate_cold 0.002", "scores": {"class_score": 0.0017347335815429688}, "domain": "pixel"}, {"position": {"minX": -34.8125, "minY": 110.25, "maxX": 246.75, "maxY": 138.75}, "class_id": 0, "box_caption": "plate_cold 0.002", "scores": {"class_score": 0.0017147064208984375}, "domain": "pixel"}, {"position": {"minX": 577.0, "minY": 145.5, "maxX": 749.0, "maxY": 248.5}, "class_id": 0, "box_caption": "plate_cold 0.002", "scores": {"class_score": 0.0016994476318359375}, "domain": "pixel"}, {"position": {"minX": -21.1875, "minY": 177.25, "maxX": 147.75, "maxY": 186.5}, "class_id": 0, "box_caption": "plate_cold 0.002", "scores": {"class_score": 0.001689910888671875}, "domain": "pixel"}, {"position": {"minX": 138.0, "minY": 199.5, "maxX": 661.5, "maxY": 210.5}, "class_id": 0, "box_caption": "plate_cold 0.002", "scores": {"class_score": 0.00168609619140625}, "domain": "pixel"}, {"position": {"minX": 357.5, "minY": 263.0, "maxX": 952.5, "maxY": 398.0}, "class_id": 0, "box_caption": "plate_cold 0.002", "scores": {"class_score": 0.0016832351684570312}, "domain": "pixel"}, {"position": {"minX": 23.4375, "minY": 213.0, "maxX": 181.0, "maxY": 224.0}, "class_id": 0, "box_caption": "plate_cold 0.002", "scores": {"class_score": 0.0016736984252929688}, "domain": "pixel"}, {"position": {"minX": 572.5, "minY": 184.375, "maxX": 647.5, "maxY": 224.875}, "class_id": 0, "box_caption": "plate_cold 0.002", "scores": {"class_score": 0.0016584396362304688}, "domain": "pixel"}, {"position": {"minX": -17.875, "minY": 111.75, "maxX": 225.25, "maxY": 125.125}, "class_id": 0, "box_caption": "plate_cold 0.002", "scores": {"class_score": 0.0016584396362304688}, "domain": "pixel"}, {"position": {"minX": -274.25, "minY": 18.484375, "maxX": 369.25, "maxY": 63.6875}, "class_id": 0, "box_caption": "plate_cold 0.002", "scores": {"class_score": 0.0016574859619140625}, "domain": "pixel"}, {"position": {"minX": 67.375, "minY": 257.75, "maxX": 556.0, "maxY": 303.75}, "class_id": 0, "box_caption": "plate_cold 0.002", "scores": {"class_score": 0.0016508102416992188}, "domain": "pixel"}, {"position": {"minX": -19.90625, "minY": 153.0, "maxX": 147.375, "maxY": 163.75}, "class_id": 0, "box_caption": "plate_cold 0.002", "scores": {"class_score": 0.0016412734985351562}, "domain": "pixel"}, {"position": {"minX": 405.5, "minY": 252.5, "maxX": 634.5, "maxY": 278.0}, "class_id": 0, "box_caption": "plate_cold 0.002", "scores": {"class_score": 0.001621246337890625}, "domain": "pixel"}, {"position": {"minX": 57.25, "minY": 242.875, "maxX": 602.0, "maxY": 277.25}, "class_id": 0, "box_caption": "plate_cold 0.002", "scores": {"class_score": 0.0016193389892578125}, "domain": "pixel"}, {"position": {"minX": 28.625, "minY": 232.25, "maxX": 244.375, "maxY": 255.5}, "class_id": 0, "box_caption": "plate_cold 0.002", "scores": {"class_score": 0.001598358154296875}, "domain": "pixel"}, {"position": {"minX": -10.75, "minY": 203.625, "maxX": 279.5, "maxY": 219.125}, "class_id": 0, "box_caption": "plate_cold 0.002", "scores": {"class_score": 0.0015954971313476562}, "domain": "pixel"}, {"position": {"minX": 559.5, "minY": 189.625, "maxX": 673.5, "maxY": 231.375}, "class_id": 0, "box_caption": "plate_cold 0.002", "scores": {"class_score": 0.0015554428100585938}, "domain": "pixel"}, {"position": {"minX": 130.625, "minY": 193.625, "maxX": 618.5, "maxY": 201.625}, "class_id": 0, "box_caption": "plate_cold 0.002", "scores": {"class_score": 0.0015535354614257812}, "domain": "pixel"}, {"position": {"minX": 277.0, "minY": 209.25, "maxX": 515.5, "maxY": 220.5}, "class_id": 0, "box_caption": "plate_cold 0.002", "scores": {"class_score": 0.001544952392578125}, "domain": "pixel"}, {"position": {"minX": 266.75, "minY": 292.5, "maxX": 881.0, "maxY": 320.0}, "class_id": 0, "box_caption": "plate_cold 0.002", "scores": {"class_score": 0.0015439987182617188}, "domain": "pixel"}, {"position": {"minX": -329.5, "minY": 227.5, "maxX": 461.0, "maxY": 423.0}, "class_id": 0, "box_caption": "plate_cold 0.002", "scores": {"class_score": 0.0015392303466796875}, "domain": "pixel"}, {"position": {"minX": 428.75, "minY": 156.0, "maxX": 648.5, "maxY": 169.5}, "class_id": 0, "box_caption": "plate_cold 0.002", "scores": {"class_score": 0.001537322998046875}, "domain": "pixel"}, {"position": {"minX": 278.0, "minY": 97.3125, "maxX": 602.5, "maxY": 107.0625}, "class_id": 0, "box_caption": "plate_cold 0.002", "scores": {"class_score": 0.0015268325805664062}, "domain": "pixel"}, {"position": {"minX": 226.0, "minY": 288.75, "maxX": 921.0, "maxY": 353.75}, "class_id": 0, "box_caption": "plate_cold 0.002", "scores": {"class_score": 0.0015239715576171875}, "domain": "pixel"}, {"position": {"minX": 40.875, "minY": 143.625, "maxX": 303.0, "maxY": 162.375}, "class_id": 0, "box_caption": "plate_cold 0.002", "scores": {"class_score": 0.0015211105346679688}, "domain": "pixel"}, {"position": {"minX": 113.625, "minY": 255.375, "maxX": 216.125, "maxY": 266.75}, "class_id": 0, "box_caption": "plate_cold 0.002", "scores": {"class_score": 0.0015201568603515625}, "domain": "pixel"}, {"position": {"minX": 442.0, "minY": -110.75, "maxX": 738.0, "maxY": 206.75}, "class_id": 0, "box_caption": "plate_cold 0.002", "scores": {"class_score": 0.0015153884887695312}, "domain": "pixel"}, {"position": {"minX": 6.328125, "minY": 206.125, "maxX": 48.6875, "maxY": 228.875}, "class_id": 0, "box_caption": "plate_cold 0.002", "scores": {"class_score": 0.0015096664428710938}, "domain": "pixel"}, {"position": {"minX": 335.75, "minY": -9.296875, "maxX": 910.0, "maxY": 61.8125}, "class_id": 0, "box_caption": "plate_cold 0.001", "scores": {"class_score": 0.001499176025390625}, "domain": "pixel"}, {"position": {"minX": 16.875, "minY": 96.625, "maxX": 429.5, "maxY": 105.75}, "class_id": 0, "box_caption": "plate_cold 0.001", "scores": {"class_score": 0.0014982223510742188}, "domain": "pixel"}, {"position": {"minX": 78.1875, "minY": 246.375, "maxX": 264.5, "maxY": 259.25}, "class_id": 0, "box_caption": "plate_cold 0.001", "scores": {"class_score": 0.0014934539794921875}, "domain": "pixel"}, {"position": {"minX": 13.4375, "minY": 238.375, "maxX": 91.5625, "maxY": 264.5}, "class_id": 0, "box_caption": "plate_cold 0.001", "scores": {"class_score": 0.00148773193359375}, "domain": "pixel"}, {"position": {"minX": -184.75, "minY": 210.75, "maxX": 217.5, "maxY": 436.25}, "class_id": 0, "box_caption": "plate_cold 0.001", "scores": {"class_score": 0.0014753341674804688}, "domain": "pixel"}, {"position": {"minX": 59.25, "minY": 258.0, "maxX": 478.25, "maxY": 394.0}, "class_id": 0, "box_caption": "plate_cold 0.001", "scores": {"class_score": 0.0014743804931640625}, "domain": "pixel"}, {"position": {"minX": 26.0, "minY": 235.875, "maxX": 220.875, "maxY": 250.125}, "class_id": 0, "box_caption": "plate_cold 0.001", "scores": {"class_score": 0.00146484375}, "domain": "pixel"}, {"position": {"minX": -75.625, "minY": 96.875, "maxX": 352.5, "maxY": 153.5}, "class_id": 0, "box_caption": "plate_cold 0.001", "scores": {"class_score": 0.0014562606811523438}, "domain": "pixel"}, {"position": {"minX": 60.5, "minY": 124.125, "maxX": 487.5, "maxY": 158.375}, "class_id": 0, "box_caption": "plate_cold 0.001", "scores": {"class_score": 0.0014429092407226562}, "domain": "pixel"}, {"position": {"minX": 212.375, "minY": -50.1875, "maxX": 501.5, "maxY": 104.9375}, "class_id": 0, "box_caption": "plate_cold 0.001", "scores": {"class_score": 0.0014400482177734375}, "domain": "pixel"}, {"position": {"minX": 33.375, "minY": 214.625, "maxX": 438.0, "maxY": 227.125}, "class_id": 0, "box_caption": "plate_cold 0.001", "scores": {"class_score": 0.0014362335205078125}, "domain": "pixel"}, {"position": {"minX": 350.0, "minY": 184.0, "maxX": 570.0, "maxY": 192.75}, "class_id": 0, "box_caption": "plate_cold 0.001", "scores": {"class_score": 0.0014276504516601562}, "domain": "pixel"}, {"position": {"minX": -17.75, "minY": 207.625, "maxX": 222.75, "maxY": 217.375}, "class_id": 0, "box_caption": "plate_cold 0.001", "scores": {"class_score": 0.0014219284057617188}, "domain": "pixel"}, {"position": {"minX": 303.5, "minY": 117.125, "maxX": 586.5, "maxY": 147.375}, "class_id": 0, "box_caption": "plate_cold 0.001", "scores": {"class_score": 0.0014190673828125}, "domain": "pixel"}, {"position": {"minX": 6.5, "minY": 173.5, "maxX": 330.25, "maxY": 200.0}, "class_id": 0, "box_caption": "plate_cold 0.001", "scores": {"class_score": 0.0014190673828125}, "domain": "pixel"}, {"position": {"minX": -19.90625, "minY": -78.25, "maxX": 72.125, "maxY": 215.75}, "class_id": 0, "box_caption": "plate_cold 0.001", "scores": {"class_score": 0.0014019012451171875}, "domain": "pixel"}, {"position": {"minX": -229.0, "minY": -155.125, "maxX": 268.5, "maxY": 206.875}, "class_id": 0, "box_caption": "plate_cold 0.001", "scores": {"class_score": 0.0013990402221679688}, "domain": "pixel"}, {"position": {"minX": 111.875, "minY": 261.75, "maxX": 217.125, "maxY": 272.75}, "class_id": 0, "box_caption": "plate_cold 0.001", "scores": {"class_score": 0.0013980865478515625}, "domain": "pixel"}, {"position": {"minX": 420.5, "minY": -17.90625, "maxX": 605.5, "maxY": 135.125}, "class_id": 0, "box_caption": "plate_cold 0.001", "scores": {"class_score": 0.0013952255249023438}, "domain": "pixel"}, {"position": {"minX": 240.0, "minY": 181.875, "maxX": 486.0, "maxY": 194.625}, "class_id": 0, "box_caption": "plate_cold 0.001", "scores": {"class_score": 0.0013866424560546875}, "domain": "pixel"}, {"position": {"minX": 12.0, "minY": 230.75, "maxX": 981.0, "maxY": 495.25}, "class_id": 0, "box_caption": "plate_cold 0.001", "scores": {"class_score": 0.0013818740844726562}, "domain": "pixel"}, {"position": {"minX": 129.125, "minY": 136.75, "maxX": 424.0, "maxY": 166.0}, "class_id": 0, "box_caption": "plate_cold 0.001", "scores": {"class_score": 0.0013799667358398438}, "domain": "pixel"}, {"position": {"minX": 159.75, "minY": 229.5, "maxX": 552.0, "maxY": 260.5}, "class_id": 0, "box_caption": "plate_cold 0.001", "scores": {"class_score": 0.0013570785522460938}, "domain": "pixel"}, {"position": {"minX": 333.75, "minY": 150.25, "maxX": 568.5, "maxY": 168.5}, "class_id": 0, "box_caption": "plate_cold 0.001", "scores": {"class_score": 0.001354217529296875}, "domain": "pixel"}, {"position": {"minX": 552.0, "minY": 121.125, "maxX": 774.0, "maxY": 238.375}, "class_id": 0, "box_caption": "plate_cold 0.001", "scores": {"class_score": 0.0013494491577148438}, "domain": "pixel"}, {"position": {"minX": -233.375, "minY": -19.25, "maxX": 389.0, "maxY": 148.875}, "class_id": 0, "box_caption": "plate_cold 0.001", "scores": {"class_score": 0.0013456344604492188}, "domain": "pixel"}, {"position": {"minX": -98.0, "minY": 121.0, "maxX": 437.5, "maxY": 138.75}, "class_id": 0, "box_caption": "plate_cold 0.001", "scores": {"class_score": 0.0013446807861328125}, "domain": "pixel"}, {"position": {"minX": -54.5, "minY": 129.75, "maxX": 391.0, "maxY": 150.0}, "class_id": 0, "box_caption": "plate_cold 0.001", "scores": {"class_score": 0.001338958740234375}, "domain": "pixel"}, {"position": {"minX": 421.0, "minY": 193.0, "maxX": 687.0, "maxY": 278.0}, "class_id": 0, "box_caption": "plate_cold 0.001", "scores": {"class_score": 0.0013322830200195312}, "domain": "pixel"}, {"position": {"minX": 96.625, "minY": 216.125, "maxX": 358.5, "maxY": 227.125}, "class_id": 0, "box_caption": "plate_cold 0.001", "scores": {"class_score": 0.0013189315795898438}, "domain": "pixel"}, {"position": {"minX": 81.875, "minY": 157.0, "maxX": 355.0, "maxY": 170.5}, "class_id": 0, "box_caption": "plate_cold 0.001", "scores": {"class_score": 0.0013170242309570312}, "domain": "pixel"}, {"position": {"minX": -160.75, "minY": 22.125, "maxX": 218.25, "maxY": 83.875}, "class_id": 0, "box_caption": "plate_cold 0.001", "scores": {"class_score": 0.0013151168823242188}, "domain": "pixel"}, {"position": {"minX": 9.875, "minY": 182.0, "maxX": 227.5, "maxY": 193.5}, "class_id": 0, "box_caption": "plate_cold 0.001", "scores": {"class_score": 0.0013113021850585938}, "domain": "pixel"}, {"position": {"minX": 480.5, "minY": 246.75, "maxX": 583.5, "maxY": 278.75}, "class_id": 0, "box_caption": "plate_cold 0.001", "scores": {"class_score": 0.0013093948364257812}, "domain": "pixel"}, {"position": {"minX": 60.75, "minY": 216.75, "maxX": 299.5, "maxY": 226.0}, "class_id": 0, "box_caption": "plate_cold 0.001", "scores": {"class_score": 0.0013036727905273438}, "domain": "pixel"}, {"position": {"minX": 444.75, "minY": 183.625, "maxX": 579.0, "maxY": 195.375}, "class_id": 0, "box_caption": "plate_cold 0.001", "scores": {"class_score": 0.001285552978515625}, "domain": "pixel"}, {"position": {"minX": 363.0, "minY": 171.125, "maxX": 633.5, "maxY": 184.375}, "class_id": 0, "box_caption": "plate_cold 0.001", "scores": {"class_score": 0.0012807846069335938}, "domain": "pixel"}, {"position": {"minX": 6.9375, "minY": 219.0, "maxX": 163.25, "maxY": 231.0}, "class_id": 0, "box_caption": "plate_cold 0.001", "scores": {"class_score": 0.0012750625610351562}, "domain": "pixel"}, {"position": {"minX": 22.0625, "minY": 108.25, "maxX": 257.0, "maxY": 131.125}, "class_id": 0, "box_caption": "plate_cold 0.001", "scores": {"class_score": 0.0012636184692382812}, "domain": "pixel"}, {"position": {"minX": 3.5, "minY": 167.0, "maxX": 609.0, "maxY": 300.5}, "class_id": 0, "box_caption": "plate_cold 0.001", "scores": {"class_score": 0.001262664794921875}, "domain": "pixel"}, {"position": {"minX": 18.0, "minY": 193.625, "maxX": 425.5, "maxY": 201.375}, "class_id": 0, "box_caption": "plate_cold 0.001", "scores": {"class_score": 0.0012617111206054688}, "domain": "pixel"}, {"position": {"minX": 118.375, "minY": 117.5625, "maxX": 397.5, "maxY": 145.25}, "class_id": 0, "box_caption": "plate_cold 0.001", "scores": {"class_score": 0.0012578964233398438}, "domain": "pixel"}, {"position": {"minX": -6.359375, "minY": 215.375, "maxX": 26.015625, "maxY": 235.125}, "class_id": 0, "box_caption": "plate_cold 0.001", "scores": {"class_score": 0.0012578964233398438}, "domain": "pixel"}, {"position": {"minX": 27.875, "minY": 212.25, "maxX": 239.625, "maxY": 225.75}, "class_id": 0, "box_caption": "plate_cold 0.001", "scores": {"class_score": 0.001251220703125}, "domain": "pixel"}, {"position": {"minX": 498.25, "minY": 204.25, "maxX": 675.0, "maxY": 248.0}, "class_id": 0, "box_caption": "plate_cold 0.001", "scores": {"class_score": 0.001251220703125}, "domain": "pixel"}, {"position": {"minX": 461.75, "minY": 147.5, "maxX": 635.0, "maxY": 170.5}, "class_id": 0, "box_caption": "plate_cold 0.001", "scores": {"class_score": 0.0012226104736328125}, "domain": "pixel"}, {"position": {"minX": 281.0, "minY": 132.375, "maxX": 649.0, "maxY": 149.625}, "class_id": 0, "box_caption": "plate_cold 0.001", "scores": {"class_score": 0.0012178421020507812}, "domain": "pixel"}, {"position": {"minX": 317.5, "minY": 109.625, "maxX": 697.0, "maxY": 134.125}, "class_id": 0, "box_caption": "plate_cold 0.001", "scores": {"class_score": 0.0012178421020507812}, "domain": "pixel"}, {"position": {"minX": -66.25, "minY": 209.25, "maxX": 343.25, "maxY": 229.5}, "class_id": 0, "box_caption": "plate_cold 0.001", "scores": {"class_score": 0.001216888427734375}, "domain": "pixel"}, {"position": {"minX": 131.5, "minY": 235.5, "maxX": 419.5, "maxY": 268.0}, "class_id": 0, "box_caption": "plate_cold 0.001", "scores": {"class_score": 0.0012159347534179688}, "domain": "pixel"}, {"position": {"minX": -26.25, "minY": 229.5, "maxX": 294.75, "maxY": 263.75}, "class_id": 0, "box_caption": "plate_cold 0.001", "scores": {"class_score": 0.0012035369873046875}, "domain": "pixel"}, {"position": {"minX": 395.5, "minY": 108.0, "maxX": 629.5, "maxY": 129.0}, "class_id": 0, "box_caption": "plate_cold 0.001", "scores": {"class_score": 0.001201629638671875}, "domain": "pixel"}], "class_labels": {"0": "plate_cold"}}