{"box_data": [{"position": {"minX": -11.75, "minY": 127.6875, "maxX": 673.0, "maxY": 263.0}, "class_id": 0, "box_caption": "plate_cold 0.749", "scores": {"class_score": 0.7490234375}, "domain": "pixel"}, {"position": {"minX": 0.75, "minY": -43.5, "maxX": 656.0, "maxY": 132.25}, "class_id": 0, "box_caption": "plate_cold 0.226", "scores": {"class_score": 0.2257080078125}, "domain": "pixel"}, {"position": {"minX": -31.75, "minY": 268.75, "maxX": 665.0, "maxY": 383.25}, "class_id": 0, "box_caption": "plate_cold 0.090", "scores": {"class_score": 0.08978271484375}, "domain": "pixel"}, {"position": {"minX": -223.0, "minY": -58.875, "maxX": 367.5, "maxY": 206.125}, "class_id": 0, "box_caption": "plate_cold 0.008", "scores": {"class_score": 0.007709503173828125}, "domain": "pixel"}, {"position": {"minX": -35.0, "minY": 6.5, "maxX": 697.0, "maxY": 157.625}, "class_id": 0, "box_caption": "plate_cold 0.004", "scores": {"class_score": 0.0035648345947265625}, "domain": "pixel"}, {"position": {"minX": 24.0, "minY": 327.75, "maxX": 666.0, "maxY": 387.25}, "class_id": 0, "box_caption": "plate_cold 0.003", "scores": {"class_score": 0.00312042236328125}, "domain": "pixel"}, {"position": {"minX": 333.5, "minY": -60.1875, "maxX": 803.5, "maxY": 135.5}, "class_id": 0, "box_caption": "plate_cold 0.002", "scores": {"class_score": 0.00231170654296875}, "domain": "pixel"}, {"position": {"minX": 3.0, "minY": 104.25, "maxX": 663.0, "maxY": 158.5}, "class_id": 0, "box_caption": "plate_cold 0.002", "scores": {"class_score": 0.0019359588623046875}, "domain": "pixel"}, {"position": {"minX": 47.5, "minY": 149.75, "maxX": 695.5, "maxY": 240.0}, "class_id": 0, "box_caption": "plate_cold 0.002", "scores": {"class_score": 0.0018510818481445312}, "domain": "pixel"}, {"position": {"minX": 488.5, "minY": 113.8125, "maxX": 656.5, "maxY": 146.375}, "class_id": 0, "box_caption": "plate_cold 0.001", "scores": {"class_score": 0.0010852813720703125}, "domain": "pixel"}, {"position": {"minX": -121.375, "minY": -86.125, "maxX": 307.0, "maxY": 162.5}, "class_id": 0, "box_caption": "plate_cold 0.001", "scores": {"class_score": 0.001018524169921875}, "domain": "pixel"}], "class_labels": {"0": "plate_cold"}}